{
	"package": {
		"productName": "SuMentor",
		"version": "0.2.1"
	},
	"build": {
		"distDir": "../dist",
		"devPath": "http://localhost:5174",
		"beforeDevCommand": "pnpm vite:dev",
		"beforeBuildCommand": "pnpm vite:build"
	},
	"tauri": {
		"bundle": {
			"active": true,
			"targets": "all",
			"identifier": "su-mentor.mcoca.dev",
			"icon": [
				"icons/32x32.png",
				"icons/128x128.png",
				"icons/128x128@2x.png",
				"icons/icon.icns",
				"icons/icon.ico"
			],
			"resources": [
				"resources/*"
			],
			"externalBin": [],
			"copyright": "",
			"category": "DeveloperTool",
			"shortDescription": "",
			"longDescription": "",
			"deb": {
				"depends": []
			},
			"macOS": {
				"frameworks": [],
				"exceptionDomain": "",
				"signingIdentity": null,
				"providerShortName": null,
				"entitlements": null
			},
			"windows": {
				"certificateThumbprint": null,
				"digestAlgorithm": "sha256",
				"timestampUrl": ""
			}
		},
		"updater": {
			"active": false
		},
		"allowlist": {
			"all": true
		},
		"windows": [
			{
				"title": "SuMentor",
				"width": 800,
				"minWidth": 650,
				"height": 540,
				"minHeight": 200,
				"resizable": true,
				"fullscreen": false
			}
		],
		"security": {
			"csp": null
		}
	}
}
